{
  "一．Java基础": [
    "一．Java基础",
    "1.1 重载和重写的区别（了解）",
    "1.2 String和StringBuffer,StringBuilder 的区别是什么？Strin",
    "1.3 自动装箱与拆箱(了解)",
    "1.4 == 与 equals (必会)",
    "1.5 关于final关键字的一些总结(必会)",
    "1.6 Java 中的异常处理(了解)",
    "1.7 error 和 exception 的区别?(了解) ",
    "1.8 接口和抽象类的区别是什么(必会)",
    "1.9 什么是单例模式？有几种？(必会)",
    "1.10 手写冒泡排序？(必会)",
    "1.11 BIO、NIO、AIO 有什么区别？(了解) ",
    "1.12 常见的数据结构有哪些？(了解)",
    "1.13 Java集合体系有什么?(必会)",
    "1.14 List 的三个子类的特点(必会)",
    "1.15 List 和 Map、Set 的区别(必会)",
    "1.16 HashMap底层实现原理(必会)",
    "1.17 谈一下 hashMap 中什么时候需要进行扩容，扩容 resize()又是如何实现的？(高薪",
    "1.18 ConcurrentHashMap特点(高薪常问)",
    "1.19 HashTable(了解) ",
    "1.20 HashMap 和 HashTable 有什么区别?(必会)",
    "1.21 HashMap，HashTable，ConcurrentHashMap之间的区别，及性能对",
    "1.22 什么是线程?线程和进程的区别?(必会)",
    "1.23 创建线程有几种方式(必会)",
    "1.24 线程的基本方法有什么?(必会)",
    "1.25 在 java 中 wait 和 sleep 方法的不同？(必会)",
    "1.26 线程池原理(高薪常问)",
    "1.27 线程执行的顺序(高薪常问)",
    "1.28 线程池的核心参数有哪些？(高薪常问)",
    "1.29 死锁产生的条件以及如何避免？(高薪常问)",
    "1.30 JVM是什么？JVM的基本结构 (高薪常问)",
    "1.31 JVM内存结构(高薪常问)",
    "1.32 类的加载, 类加载器的种类, 类加载机制(高薪常问)",
    "1.33 什么是GC(高薪常问)",
    "1.34 JVM调优的工具有哪些？(高薪常问)",
    "1.35 常用的 JVM 调优的参数都有哪些？(高薪常问)"
  ],
  "二．Java Web ": [
    "二．Java Web ",
    "2.1 JDBC 技术",
    "2.1.1 说下原JDBC操作数据库流程？",
    "2.1.2 说说事务的概念，在JDBC编程中处理事务的步骤。",
    "2.1.3 JDBC的脏读是什么？哪种数据库隔离级别能防止脏读？",
    "3.1 网路通讯部分",
    "3.1.1 TCP与UDP区别？",
    "3.1.2 说一下什么是Http协议？",
    "3.1.3 get与post请求区别？",
    "3.1.4 http中重定向和请求转发的区别？",
    "4.1 Cookie 和 Session",
    "5.1 Jsp和Servlet",
    "5.1.2 Jsp和Servlet的区别",
    "5.1.3 JSP九大内置对象",
    "5.1.4 JSP的三大指令",
    "5.1.5 七大动作",
    "6.1 Ajax ",
    "6.1.1 谈谈你对 Ajax 的认识？（了解）",
    "6.1.2 Ajax创建的过程？（了解）",
    "6.1.3 阐述一下异步加载 JS？（了解）",
    "6.1.4 ajax 请求时，如何解释 json 数据？（了解）",
    "6.1.5 Ajax 提交请求 默认是 异步还是同步,怎么改成同步？（了解）",
    "6.1.6 如何解决 ajax 跨域问题？（了解）",
    "6.1.7 Ajax 的优势（了解）",
    "6.1.8 请介绍下 Jsonp 原理（了解）"
  ],
  "三．数据库": [
    "三．数据库",
    "3.1 SQL 之连接查询(必会)",
    "3.2 SQL 之聚合函数(必会)",
    "3.3 SQL 之 SQL 注入(必会)",
    "3.4 SQL Select 语句完整的执行顺序: (必会)",
    "3.5 存储引擎（高薪常问）",
    "3.5.1 概念",
    "3.5.2 InnoDB",
    "3.5.3 TokuDB",
    "3.5.4 MyIASM",
    "3.5.5 Memory",
    "3.6 索引（高薪常问）",
    "3.6.1 普通索引",
    "3.6.2 唯一索引",
    "3.6.3 主键索引",
    "3.6.4 组合索引",
    "3.6.5 全文索引",
    "3.6.6 索引的优点",
    "3.6.7 索引的缺点",
    "3.6.8 常见索引原则",
    "3.7 索引原理（了解）",
    "3.7.1 磁盘IO与预读",
    "3.7.2 B+树",
    "3.7.3 B+树的查找过程",
    "3.7.4 B+树性质",
    "3.7.5 聚焦索引和辅助索引",
    "3.8 数据库三范式(必会)",
    "3.8.1 第一范式(1st NF －First Normal Fromate)",
    "3.8.2 第二范式(2nd NF－Second Normal Fromate)",
    "3.8.3 第三范式(3rd NF－ Third Normal Fromate)",
    "3.9 数据库事务(必会)",
    "3.9.1 事务(TRANSACTION)",
    "3.9.2 事务控制语句",
    "3.9.3 MySQL 事务处理主要有两种方法：",
    "3.9.4 事务的四种隔离级别",
    "3.10 存储过程（高薪常问）",
    "3.11 数据库并发策略（高薪常问）",
    "3.11.1 乐观锁",
    "3.11.2 悲观锁",
    "3.11.3 两种锁的使用场景",
    "3.11.4 乐观锁常见的两种实现式版本号机制",
    "3.11.5 乐观锁的缺点",
    "3.11.6 时间戳",
    "3.12 触发器（高薪常问）",
    "3.13 数据库锁（高薪常问）",
    "3.13.1 行级锁",
    "3.13.2 表级锁",
    "3.13.3 页级锁",
    "3.14 基于 Redis 分布式锁（高薪常问）",
    "3.15 分区分表（高薪常问）",
    "3.16 应该使用哪一种方式来实施数据库分库分表，这要看数据库中数据量的瓶颈所在，并综合项目的业务类",
    "3.17 MySQL 读写分离（高薪常问）",
    "3.18 MySQL 常用 30 种 SQL 查询语句优化方法(必会)",
    "3.19 数据库优化方案整理（高薪常问）",
    "3.19.1 优化说明",
    "3.19.2 优化方向 ",
    "3.19.3 优化方案",
    "3.20 oracle和mysql的分页语句？（必会）",
    "3.20.1 oracle",
    "3.20.2 mysql"
  ],
  "四. Mybatis框架 ": [
    "四. Mybatis框架 ",
    "4.8 MyBatis实现一对一有几种方式?具体怎么操作的？（必会）",
    "4.9 Mybatis是否支持延迟加载？如果支持，它的实现原理是什么？（必会）",
    "4.10 Mybatis的一级.二级缓存（必会）"
  ],
  "五．Spring框架": [
    "五．Spring框架",
    "5.1 Spring是什么?(了解）",
    "5.2 Spring的AOP理解？（必会）",
    "5.3 Spring的IOC理解？（必会）",
    "5.4 BeanFactory和ApplicationContext有什么区别？（了解）",
    "5.5 请解释Spring Bean的生命周期？（必会）",
    "5.6 解释Spring支持的几种bean的作用域。（必会）",
    "5.7 spring常见的注解（必会）",
    "5.8 Spring框架中的单例Beans是线程安全的么？（了解）",
    "5.9 Spring如何处理线程并发问题？（必会）",
    "5.10 Spring基于xml注入bean的几种方式（必会）",
    "5.11 Spring 框架中都用到了哪些设计模式？（高薪必问）",
    "5.12 Spring事务的实现方式和实现原理（高薪必问）",
    "5.13 解释一下Spring AOP里面的几个名词（了解）",
    "5.14 Spring通知有哪些类型？（了解）"
  ],
  "六．SpringMVC框架": [
    "六．SpringMVC框架",
    "6.1 什么是SpringMVC ？简单介绍下你对SpringMVC的理解?（了解）",
    "6.2 SpringMVC的流程？（必会）",
    "6.3 SpringMVC的主要组件？（必会）",
    "6.4 SpringMVC和Struts2的区别有哪些?（必问）",
    "6.5 SpringMVC怎么和Ajax相互调用的？（必会）",
    "6.6 如何解决Post请求中文乱码问题，Get的又如何处理呢？（了解）",
    "6.7 SpringMVC常用的注解有哪些？（必问）",
    "6.8 SpringMVC里面拦截器是怎么写的？（了解）"
  ],
  "七．Saas项目": [
    "七．Saas项目",
    "7.1 介绍话术 ",
    "7.2 名词与概念",
    "7.3 货运管理业务讲解：",
    "7.4 开发环境与技术：",
    "7.5 项目亮点设计",
    "7.6 项目技术与业务",
    "7.6.1 分页查询业务",
    "7.6.1.1传统分页",
    "7.6.1.2 PageHelper",
    "7.6.2 权限",
    "7.6.3 动态构造菜单",
    "7.6.4 Shiro",
    "7.7 Dubbo",
    "7.7.1 Dubbo的项目架构",
    "7.7.2 什么是dubbo? ",
    "7.7.3 Dubbo的实现原理图如下",
    "7.7.4 节点角色说明",
    "7.7.5 调用关系说明",
    "7.7.6 在实际开发的场景中应该如何选择RPC框架",
    "7.7.7 Dubbo面试问题汇总： ",
    "7.7.7.1 什么是缺省协议？",
    "7.7.7.2 为什么不能传大包",
    "7.7.7.3 Dubbo中的zookeeper做注册中心，如果注册中心集群都挂掉，发布者和订阅者还",
    "7.7.7.4 dubbo服务的负载均衡策略？",
    "7.7.7.5 Dubbo 在安全机制方面是如何解决的？",
    "7.7.7.6 dubbo链接注册中心和直连有什么区别？",
    "7.7.7.7 dubbo服务集群的容错模式",
    "7.8 Zookeeper",
    "7.8.1 Zookeeper是如何实现配置维护.组服务.分布式消息队列等等服务的呢？",
    "7.8.2 简述一下你对Znode的理解",
    "7.8.3 Zookeeper角色说明",
    "7.8.4 角色调用关系说明",
    "7.8.5 Zookeeper的核心是什么？",
    "7.8.6 Zookeeper中的每个Server有几种状态？",
    "7.8.7 Zookeeper的节点数据操作流程",
    "7.8.8 为什么zookeeper集群的数目，一般为奇数个？",
    "7.8.9 经典实例：Zookeeper分布式锁的应用场景",
    "7.9 POI",
    "7.9.1 POI的介绍",
    "7.9.2 POI项目中的使用，主要用在哪些地方？<项目中主要使用在出货表打印，合同上传，销售报表等",
    "7.9.3 Excel报表导出流程：",
    "7.9.4 百万级数据导出",
    "7.10 WebService技术使用",
    "7.10.1 技术描述",
    "7.10.2 面试问题汇总：",
    "7.10.3 webService的三大规范是什么？",
    "7.10.4 除了webService，还有什么技术可以实现内部程序调用其他网站服务？",
    "7.10.5 如何以JAVA的形式启动当前web应用",
    "7.10.6 远程通信的几种选择（RPC，Webservice，RMI，JMS的区别）",
    "7.10.7 在项目中常用的注解有哪些？",
    "7.10.8 webService的三要素是什么？",
    "7.10.9 项目中是如何使用CXF进行外部接口调用的？",
    "7.11 echarts在项目中的应用？",
    "7.12 Quartz的应用",
    "7.13 PDF导出",
    "7.13.1 常用的pdf技术有哪些？",
    "7.13.2 JasperReport 的生命周期是？",
    "7.13.3 JasperReport 的执行流程是什么？",
    "7.13.4 在项目中PDF导出的使用？",
    "7.14 RabbitMQ",
    "7.14.1 什么是RabbitMQ？",
    "7.14.2 为什么要使用RabbitMQ？Rabbit有什么优点？",
    "7.14.3 RabbitMQ有什么缺点？",
    "7.14.4 RabbitMQ的工作模式？",
    "7.14.5 如何保证RabbitMQ高可用？",
    "7.14.6 如何保证RabbitMQ消息不被重复消费？",
    "7.14.7 如何保证RabbitMQ消息可靠传输？",
    "7.14.8 如何保证RabbitMQ消息的顺序性？",
    "7.14.10 RabbitMQ消息堆积处理",
    "7.14.11 RabbitMQ消息丢失解决方案",
    "7.14.12 RabbitMQ宕机了怎么处理",
    "7.14.13 RabbitMQ的集群",
    "7.14.14 如何解决分布式事务问题？",
    "7.14.15 常见的消息中间",
    "7.15 面试问题汇总：",
    "7.15.1 这个系统UI使用什么框架？都用到jquery easy ui的哪些组件？ ",
    "7.15.2 本系统ajax+json具体是怎么做的？action的方法返回的json是如何实现的？",
    "7.15.3 系统哪些地方使用到了json？",
    "7.15.4 你是如何将对象转成JSON或是将JSON转成对象？",
    "7.15.5 这个系统异常处理是怎么做的？",
    "7.15.6 你如何理解前端验证和后端验证，是如何实现的？",
    "7.15.7 如果我要实现某个数据非空验证，是不是写了前端验证就不用写后端验证了？",
    "7.15.8 你在使用下拉列表数据时，如果下拉列表数据过多（100条以上），你是如何让用户很快找到要",
    "7.15.9 本系统配置信息是如何规范的？ ",
    "7.15.10 系统中都包括哪些系统配置方式？ ",
    "7.15.11 你是如何和测试人员配合工作的？ ",
    "7.15.12 项目中如何进行事务管理的？",
    "7.15.13 这个项目开发过程中遇到了哪些问题？",
    "7.15.14 什么是SaaS项目？",
    "7.15.15 SaaS项目的优势是什么？",
    "7.15.16 SaaS项目合适什么项目？"
  ],
  "八.SpringBoot框架": [
    "八.SpringBoot框架",
    "8.1 SpringBoot是什么？为什么我们选择使SpringBoot开发？(必会)",
    "8.2 SpringBoot常用的starter有哪些（必会）",
    "8.3 SpringBoot自动配置的原理（高薪常问）",
    "8.4 SpringBoot如何添加【修改代码】自动重启功能（了解）",
    "8.5什么是 Spring Data？（必会）",
    "8.6 SpringBoot 的核心配置文有哪几个？它们的区别是什么？（了解）",
    "8.7 SpringBoot 的配置文件有哪几种格式?它们有什么区别？（必会）",
    "8.8 运行SpringBoot有哪几种方式？（必会）",
    "8.9 如何在 SpringBoot 启动的时候运行一些特定的代码？（了解）",
    "8.10 SpringBoot 有哪几种读取配置的方式？（了解）",
    "8.11 SpringBoot支持哪些日志框架？推荐和默认的日志框架是哪个？（必会）",
    "8.12 SpringBoot 实现热部署有哪几种方式？（必会）",
    "8.13 你如何理解 SpringBoot 配置加载顺序？（了解）",
    "8.14 SpringBoot 如何定义多套不同环境配置？（高薪常问）",
    "8.15 SpringBoot 可以兼容老Spring项目吗，如何做？（了解）",
    "8.16 保护SpringBoot 应用有哪些方法？（了解）",
    "8.17 SpringBoot 2.X 有什么新特性？与 1.X 有什么区别？（了解）"
  ],
  "九. SpringCloud框架": [
    "九. SpringCloud框架",
    "9.1 什么是SpringCloud框架？（必会）",
    "9.2 核心组件讲解：（高薪常问）",
    "9.2.1 Eureka(服务中心)（必会）",
    "9.2.2 Ribbon(负载均衡工具)（了解）",
    "9.2.3 Hystrix(熔断器)（必会）",
    "9.2.4 Zuul(服务网关)（必会）",
    "9.2.5 Config(配置中心)（了解）",
    "9.2.6 SpringCloud基于业务场景对于各个组件的讲解（了解）",
    "9.3 SpringCloud和Dubbo的区别（必会）",
    "9.4 使用SpringCloud的优缺点？（必会）",
    "9.5 服务注册和发现是什么意思？SpringCloud如何实现？（必会）",
    "9.6 负载平衡的意义什么？（必会）",
    "9.7 什么是Hystrix？它如何实现容错？ （必会）",
    "9.8 什么是Hystrix断路器？我们需要它吗？（了解）",
    "9.9 什么是Netflix Feign？它的优点是什么？（了解）",
    "9.10 什么是SpringCloud Bus？我们需要它吗？（了解）",
    "9.11 Eureka和Zookeeper注册中心的区别（高新常问）"
  ],
  "十. 乐优商城": [
    "十. 乐优商城",
    "10.1 项目介绍",
    "10.1.1 什么是微服务",
    "10.1.2 微服务有什么优势",
    "10.1.3 SOA与微服务的关系",
    "10.1.4 什么是单体架构",
    "10.1.5 单体架构的不足",
    "10.1.6 B2C",
    "10.1.6.1 什么是B2C",
    "10.1.6.2 其它的电商模式有哪些？",
    "1.B2B—企业对企业",
    "2.C2C—个人对个人",
    "3.B2B2C—企业对企业对个人",
    "4.O2O—线上对线下",
    "10.2 项目架构",
    "10.2.1 传统架构",
    "10.2.2 SOA架构",
    "10.2.3 微服务架构",
    "10.3 项目功能",
    "10.3.1 人员配置",
    "10.3.2 开发流程",
    "10.3.3 开发技术",
    "10.3.4 数据库表结构",
    "10.4 模块业务",
    "10.4.1 业务思路",
    "10.5 商品管理(CORS,RabbitMQ,OSS,Nginx) ",
    "10.5.1 表设计",
    "10.5.2 什么是SPU和SKU",
    "10.5.3 为什么不设置外键约束",
    "10.5.4 业务",
    "10.5.5 什么是跨域",
    "10.5.6 为什么有跨域问题",
    "10.5.7 解决跨域问题的方案",
    "10.5.8 CORS",
    "5.8.1 什么使CORS",
    "5.8.2 CORS原理",
    "5.8.3 实现",
    "10.5.9 为什么图片地址需要使用另外的url？",
    "10.5.10 消息中间件",
    "10.5.10.1 什么是消息中间件",
    "10.5.10.2 消息中间件的组成",
    "10.5.10.3 消息中间件模式分类",
    "10.5.10.4 消息中间件的优势",
    "10.5.10.5 消息中间件常用协议",
    "10.5.11 RabbitMQ",
    "10.5.11.1 什么是RabbitMQ？",
    "10.5.11.2 为什么要使用RabbitMQ？Rabbit有什么优点？",
    "10.5.11.3 RabbitMQ有什么缺点？",
    "10.5.11.4 RabbitMQ的工作模式？",
    "10.5.11.5 如何保证RabbitMQ高可用？",
    "10.5.11.6 如何保证RabbitMQ消息不被重复消费？",
    "10.5.11.7 如何保证RabbitMQ消息可靠传输？",
    "10.5.11.8 如何保证RabbitMQ消息的顺序性？",
    "10.5.11.10 RabbitMQ消息堆积处理",
    "10.5.11.11 RabbitMQ消息丢失解决方案",
    "10.5.11.12 RabbitMQ宕机了怎么处理",
    "10.5.11.13 RabbitMQ的集群",
    "10.5.11.14 如何解决分布式事务问题？",
    "10.5.11.15 常见的消息中间",
    "10.5.12 图片上传",
    "10.5.13 FastDFS",
    "10.5.14 Nginx",
    "10.6 商品搜索(ElasticSearch,Solr)",
    "10.6.1 简介",
    "10.6.2 功能特点",
    "10.6.3 ElasticSearch",
    "10.6.3.1 概念",
    "10.6.3.2 作用",
    "10.6.3.3 优势",
    "10.6.3.4 ElasticSearch中的倒排索引是什么？",
    "10.6.3.5 ElasticSearch中的集群、节点、索引、文档、类型是什么？",
    "10.6.3.6 ElasticSearch中的分片是什么？",
    "10.6.3.7 ElasticSearch中的副本是什么？",
    "10.6.3.8 ElasticSearch查询方式有哪几种？",
    "10.6.4 Solr",
    "10.6.4.1 概念",
    "10.6.4.2 优势",
    "10.6.4.3 工作机制",
    "10.6.5 Ik分词器",
    "10.6.5.1 什么是分词",
    "10.6.5.2 为什么要使用Ik分词器？",
    "10.6.5.3 Ik分词器的原理？",
    "10.6.5.4 ElasticSearch集成Ik分词器",
    "10.6.6 ElasticSearch和Solr对比区别是什么?",
    "10.7 页面静态化(Thymeleaf)",
    "10.7.1 业务思路",
    "10.7.2 什么是静态化",
    "10.7.3 常见的静态化技术及对比",
    "jsp",
    "freemarker  　　   ",
    "velocity",
    "thymeleaf",
    "10.8 用户注册(阿里大于)",
    "10.8.1 业务思路",
    "10.8.2 阿里大于",
    "10.9 用户登录(JWT)",
    "10.9.1 授权业务思路（登录）",
    "10.9.2 鉴权业务思路（每个微服务验证是否登录）",
    "10.9.3 什么是有状态登录？",
    "10.9.4 什么是无状态登录？",
    "10.9.5 JWT",
    "10.9.5.1 组成",
    "10.9.5.2 面试问题：",
    "10.9.5.2.1 JWT token 泄露了怎么办？(常问)",
    "10.9.5.2.2 Secret如何设计？",
    "10.9.5.2.3 注销和修改密码？",
    "10.9.5.2.4 如何解决续签问题",
    "10.9.5.2.5 如何防止令牌被盗用？",
    "10.9.6 加密技术",
    "10.10 购物车(localstorage+Redis)",
    "10.10.1 业务思路",
    "10.10.2 Html5 web存储",
    "10.10.3 Redis",
    "10.10.3.1什么是Redis",
    "10.10.3.2 Redis的存储结构有哪些",
    "10.10.3.3 Redis的优点",
    "10.10.3.4 Redis的缺点",
    "10.10.3.5 Redis的持久化",
    "10.10.3.6 RDB",
    "10.10.3.7 AOF",
    "10.10.3.8 Redis集群",
    "10.10.4 购物车存cookie里边 可以实现不登录就可以使用购物车 那么现在没有登录把商品存购",
    "10.10.5 如果用户一直添加购物车添加商品怎么办？并且他添加一次你查询一次数据库？互联网上用户那",
    "10.10.6 Redis为什么可以做缓存？项目中使用Redis的目的是什么？Redis什么时候使用",
    "10.10.7 对Redis和Memcache有没有了解,为什么选择Redis?",
    "10.10.8 Redis面试经常会问到的问题",
    "10.10.8.1 redis的过期策略以及内存淘汰机制",
    "10.10.8.2 redis和数据库双写一致性问题",
    "10.10.8.3 如何应对缓存穿透和缓存雪崩问题",
    "10.10.8.4 如何解决redis的并发竞争key问题",
    "10.10.8.5 mySQL里有2000w数据，redis中只存20w的数据，如何保证redis中",
    "10.10.8.6 redis事物的了解CAS(check-and-set 操作实现乐观锁 )?",
    "10.10.8.7 WATCH命令和基于CAS的乐观锁：",
    "10.10.8.9 redis的缓存失效策略和主键失效机制",
    "10.10.8.10 读写分离模型",
    "10.10.8.11 使用过Redis分布式锁么，它是什么回事？",
    "10.10.8.12 如果有大量的key需要设置同一时间过期，一般需要注意什么？",
    "10.10.8.13 Redis的同步机制了解么？",
    "10.10.8.14 是否使用过Redis集群，集群的原理是什么？",
    "10.11 订单系统",
    "10.11.1 业务思路",
    "10.12 支付系统",
    "10.12.1 业务思路(微信支付)",
    "10.12.2 支付接口是怎么做的？",
    "10.12.3 第一个是当两个客户同时买一件商品时库存只有一个了,怎么控制?"
  ],
  "十一．十次方项目": [
    "十一．十次方项目",
    "11.1 十次方背景",
    "11.1.1需求分析",
    "11.1.2 前后端分离的优点和必要性",
    "11.1.3 什么是前后端分离",
    "11.1.4 为什么要前后端分离",
    "11.1.5 十次方项目背景",
    "11.1.5.1 系统架构",
    "11.1.5.2 特色",
    "11.1.5.3 模块划分",
    "11.1.5.4 表结构分析",
    "11.1.5.5 API文档",
    "11.1.5.6 开发环境",
    "11.1.5.7 项目主要技术以及功能实现",
    "11.1.5.7.1 前端环境搭建",
    "11.1.5.7.2 API文档与模拟数据接口",
    "11.1.5.7.3 使用ElementUI开发管理后台",
    "11.1.5.7.4 网站前台",
    "11.1.5.7.5 系统设计与工程搭建",
    "11.1.5.7.6 微服务功能开发",
    "11.1.5.7.7 文档型数据库MongoDB",
    "11.1.5.7.8 消息中间件RabbitMQ与搜索微服务",
    "11.1.5.7.9 密码加密与微服务鉴权JWT",
    "11.1.5.7.10 SpringCloud初入江湖&SpringCloud一统天下",
    "11.1.5.7.11 爬虫",
    "11.1.5.7.12 人工智能",
    "11.2 十次方项目技术架构",
    "11.3 十次方项目面试常问问题 ",
    "11.3.1 对微服务有何了解？（了解）",
    "11.3.2 微服务架构有哪些优势？（了解）",
    "11.3.3 微服务有哪些特点？（必会）",
    "11.3.4 微服务架构如何运作？（必会）",
    "11.3.5 微服务架构的优缺点是什么？（必会）",
    "11.3.6 单片，SOA和微服务架构有什么区别？（必会）",
    "11.3.7 在使用微服务架构时，您面临哪些挑战？（必会）",
    "11.3.8 SOA和微服务架构之间的主要区别是什么？（必会）",
    "11.3.9 什么是耦合？（了解）",
    "11.3.10 什么是Rest/ Restful架构以及它的用途是什么？（了解）",
    "11.3.11 你对SpringBoot有什么了解？（必会）",
    "11.3.12 什么是Spring引导的执行器？（必会）",
    "11.3.13 什么是SpringCloud？（必会）",
    "11.3.14  SpringCloud解决了哪些问题？（必会）",
    "11.3.15 在Spring MVC应用程序中使用WebMvcTest注释有什么用处？（必会）",
    "11.3.16 你能否给出关于休息和微服务的要点？（必会）",
    "11.3.17 什么是不同类型的微服务测试？（必会）",
    "11.3.18 您对Distributed Transaction有何了解？（必会）",
    "11.3.19 什么是Idempotence以及它在哪里使用？（必会）",
    "11.3.20 什么是有界上下文？（必会）",
    "11.3.21 什么是双因素身份验证？（必会）",
    "11.3.22 双因素身份验证的凭据类型有哪些？（了解）",
    "11.3.23 什么是客户证书？（了解）",
    "11.4 十次方技术点",
    "11.4.1 MongoDB（高薪常问）",
    "11.4.1.1 什么是MongoDB",
    "11.4.1.2 MongoDB特点",
    "11.4.1.3 MongoDB体系结构",
    "11.4.1.4 MongoDB数据类型",
    "11.4.2 即时通讯（高薪常问）",
    "11.4.2.1 什么是即时通信？",
    "11.4.2.2 什么是短连接？",
    "11.4.2.3 什么是长连接？",
    "11.4.4 短连接和长连接的区别？",
    "11.4.4.1 通讯流程",
    "11.4.4.2 适用场景",
    "11.4.4.3 通讯方式",
    "11.4.3 websocket协议（了解）",
    "11.4.3.1 何为websocket协议？",
    "11.4.3.2 websocket常用事件方法？",
    "11.4.4 接口加密&加密方式（高薪常问）",
    "11.4.4.1 摘要算法",
    "11.4.4.2 对称加密",
    "11.4.4.3 非对称加密",
    "11.4.4.4 数字签名",
    "11.4.5 消息通知（必会）",
    "11.4.5.1 消息通知的业务场景",
    "11.4.5.2 消息通知与即时通讯的区别",
    "11.4.5.3 消息通知存在的问题",
    "11.4.5.3.1 数据库访问压力大",
    "11.4.5.3.2 服务器性能压力大",
    "11.4.5.3.3 改进的方法",
    "11.4.6 Redis分布式缓存（必会、高薪常问）",
    "11.4.6.1 Redis读写分离",
    "11.4.6.2 Redis性能测试",
    "11.4.6.2.1 Redis-benchmark",
    "11.4.6.2.2 TPS.QPS.RT",
    "11.4.6.3 Redis同步原理",
    "11.4.6.4 Redis的高可用Sentinel",
    "11.4.7 JUC多线程（必会、高薪常问）",
    "11.4.7.1 认识多线程",
    "11.4.7.2 什么是线程？",
    "11.4.7.3 什么是进程？",
    "11.4.7.4 进程与线程的区别？",
    "11.4.7.4 什么是线程安全？",
    "11.4.7.5 什么时候使用线程同步？",
    "11.4.7.6 线程同步机制有哪些？",
    "11.4.7.7 对死锁的理解？",
    "11.4.7.8 多线程并发的3个特性？",
    "11.4.7.9 锁优化",
    "11.4.7.10 自旋锁",
    "11.4.7.11 适应自旋锁",
    "11.4.7.12 锁消除",
    "11.4.7.13 锁粗化",
    "11.4.7.14 偏向锁",
    "11.4.7.15 轻量级锁",
    "11.4.7.16 重量锁"
  ]
}
